converter/__init__.py
converter/converter.py
dsp_metadata_conversion-1.0.3.dist-info/LICENSE
dsp_metadata_conversion-1.0.3.dist-info/METADATA
dsp_metadata_conversion-1.0.3.dist-info/WHEEL
dsp_metadata_conversion-1.0.3.dist-info/entry_points.txt
dsp_metadata_conversion-1.0.3.dist-info/top_level.txt
dsp_metadata_conversion-1.0.3.dist-info/RECORD
