Metadata-Version: 2.1
Name: dsp-metadata-conversion
Version: 1.0.3
Summary: ython CLI for converting project metadata from JSON to RDF
Home-page: https://github.com/dasch-swiss/dsp-metadata-conversion
Author: Balduin Landolt
Author-email: balduin.landolt@dasch.swiss
License: Apache 2.0
Classifier: Programming Language :: Python :: 3
Classifier: License :: OSI Approved :: Apache Software License
Classifier: Operating System :: OS Independent
Requires-Python: >=3.9.0
License-File: LICENSE
Requires-Dist: isodate ==0.6.0
Requires-Dist: owlrl ==5.2.3
Requires-Dist: pyshacl ==0.17.2
Requires-Dist: rdflib ==6.0.2
Requires-Dist: wcwidth ==0.2.5
Requires-Dist: six ==1.16.0 ; python_version >= "2.7" and python_version not in "3.0, 3.1, 3.2, 3.3"
Requires-Dist: prettytable ==2.2.1 ; python_version >= "3.6"
Requires-Dist: pyparsing ==3.0.1 ; python_version >= "3.6"
